minakicoin/__init__.py
minakicoin/main.py
minakicoin/cli/__init__.py
minakicoin/cli/address.py
minakicoin/cli/balance.py
minakicoin/cli/create.py
minakicoin/cli/history.py
minakicoin/cli/list.py
minakicoin/cli/mine.py
minakicoin/cli/mine_cpp.py
minakicoin/cli/mine_gpu.py
minakicoin/cli/mine_multiproc.py
minakicoin/cli/mine_parallel.py
minakicoin/cli/p2p.py
minakicoin/cli/send.py
minakicoin/cli/utxos.py
minakicoin/cli/wallet.py
minakicoin/config/__init__.py
minakicoin/config/config.py
minakicoin/config/loader.py
minakicoin/config/settings.py
minakicoin/config/wallet_schema.sql
minakicoin/core/__init__.py
minakicoin/core/blockchain.py
minakicoin/core/chain.py
minakicoin/core/chain_store.py
minakicoin/core/consensus.py
minakicoin/core/genesis.py
minakicoin/core/miner.py
minakicoin/core/storage.py
minakicoin/log/__init__.py
minakicoin/log/logger.py
minakicoin/models/__init__.py
minakicoin/models/block.py
minakicoin/models/block_header.py
minakicoin/models/peer.py
minakicoin/models/transactions.py
minakicoin/models/utxo.py
minakicoin/models/wallet.py
minakicoin/modules/consensus/__init__.py
minakicoin/modules/consensus/pow.py
minakicoin/modules/network/__init__.py
minakicoin/modules/network/peer_store.py
minakicoin/modules/storage/__init__.py
minakicoin/modules/storage/memory.py
minakicoin/modules/storage/transactions.py
minakicoin/modules/wallet/__init__.py
minakicoin/modules/wallet/keys.py
minakicoin/modules/wallet/wallet.py
minakicoin/p2p_node/api.py
minakicoin/p2p_node/state.py
minakicoin/p2p_node/legacy/entrypoint.py
minakicoin/p2p_node/legacy/routes.py
minakicoin/p2p_node/legacy/routes_mining.py
minakicoin/p2p_node/routes/__init__.py
minakicoin/p2p_node/routes/broadcast.py
minakicoin/p2p_node/routes/chain.py
minakicoin/p2p_node/routes/mining.py
minakicoin/p2p_node/routes/peer.py
minakicoin/p2p_node/routes/status.py
minakicoin/p2p_node/services/sync.py
minakicoin/services/block_factory.py
minakicoin/services/block_validation.py
minakicoin-0.1.6.dist-info/METADATA
minakicoin-0.1.6.dist-info/WHEEL
minakicoin-0.1.6.dist-info/entry_points.txt
minakicoin-0.1.6.dist-info/top_level.txt
minakicoin-0.1.6.dist-info/RECORD
